WordTime-0.1.dist-info/DESCRIPTION.rst
WordTime-0.1.dist-info/METADATA
WordTime-0.1.dist-info/RECORD
WordTime-0.1.dist-info/WHEEL
WordTime-0.1.dist-info/metadata.json
WordTime-0.1.dist-info/top_level.txt
wordtime/__init__.py
wordtime/menubar.py
wordtime/wordTime.py
