Metadata-Version: 2.0
Name: WordTime
Version: 0.1
Summary: A macOS menu bar item which tells the time in words.
Home-page: https://github.com/Demonstrandum/WordTime
Author: Demonstrandum
Author-email: knutsen@jetspace.co
License: GPL-3.0
Keywords: simple clock words time fuzzy
Platform: UNKNOWN
Classifier: Development Status :: 3 - Alpha
Classifier: Intended Audience :: End Users/Desktop
Classifier: Operating System :: MacOS :: MacOS X
Classifier: Programming Language :: Python :: 2
Requires-Dist: pyobjc
Requires-Dist: rumps
